[
  {
    "id": 1,
    "Nombre de película": "La noche de los faros",
    "duracion": 102,
    "director": "María González",
    "año de realización": 2018,
    "país": "Chile",
    "stock": 12,
    "valor del producto": 5500.00,
    "fecha de exhibición": "2025-10-05",
    "imagen": "../images/image1.jpg"
  },
  {
    "id": 2,
    "Nombre de película": "Ecos en la pared",
    "duracion": 121,
    "director": "Diego Ramírez",
    "año de realización": 2020,
    "país": "Argentina",
    "stock": 8,
    "valor del producto": 7200.50,
    "fecha de exhibición": "2025-10-12",
    "imagen": "../images/image2.jpg"
  },
  {
    "id": 3,
    "Nombre de película": "Verano en silencio",
    "duracion": 90,
    "director": "Ana Ruiz",
    "año de realización": 2016,
    "país": "España",
    "stock": 20,
    "valor del producto": 4300.00,
    "fecha de exhibición": "2025-09-30",
    "imagen": "../images/image3.jpg"
  },
  {
    "id": 4,
    "Nombre de película": "Ciudad de humo",
    "duracion": 138,
    "director": "Lucas Fernández",
    "año de realización": 2019,
    "país": "México",
    "stock": 5,
    "valor del producto": 9800.00,
    "fecha de exhibición": "2025-11-02",
    "imagen": "../images/image4.jpg"
  },
  {
    "id": 5,
    "Nombre de película": "La brújula perdida",
    "duracion": 115,
    "director": "Sofía Méndez",
    "año de realización": 2021,
    "país": "Perú",
    "stock": 14,
    "valor del producto": 6100.75,
    "fecha de exhibición": "2025-10-20",
    "imagen": "../images/image5.jpg"
  },
  {
    "id": 6,
    "Nombre de película": "Fragmentos de luz",
    "duracion": 80,
    "director": "Tomás Herrera",
    "año de realización": 2015,
    "país": "Colombia",
    "stock": 25,
    "valor del producto": 3200.00,
    "fecha de exhibición": "2025-09-28",
    "imagen": "../images/image6.jpg"
  },
  {
    "id": 7,
    "Nombre de película": "Último tren a Matadero",
    "duracion": 125,
    "director": "Clara Salinas",
    "año de realización": 2017,
    "país": "Chile",
    "stock": 7,
    "valor del producto": 7900.00,
    "fecha de exhibición": "2025-10-08",
    "imagen": "../images/image7.jpg"
  },
  {
    "id": 8,
    "Nombre de película": "Mariposas de concreto",
    "duracion": 108,
    "director": "Pedro Alvarado",
    "año de realización": 2022,
    "país": "Uruguay",
    "stock": 10,
    "valor del producto": 5400.00,
    "fecha de exhibición": "2025-11-15",
    "imagen": "../images/image8.jpg"
  },
  {
    "id": 9,
    "Nombre de película": "Ruta de los silencios",
    "duracion": 97,
    "director": "Isabel Torres",
    "año de realización": 2014,
    "país": "Chile",
    "stock": 18,
    "valor del producto": 4100.25,
    "fecha de exhibición": "2025-10-01",
    "imagen": "../images/image9.jpg"
  },
  {
    "id": 10,
    "Nombre de película": "Atenas en llamas",
    "duracion": 142,
    "director": "Nicolás Duarte",
    "año de realización": 2013,
    "país": "Grecia",
    "stock": 4,
    "valor del producto": 12500.00,
    "fecha de exhibición": "2025-12-01",
    "imagen": "../images/image10.jpg"
  },
  {
    "id": 11,
    "Nombre de película": "Café y metrónomo",
    "duracion": 75,
    "director": "Laura Pinto",
    "año de realización": 2024,
    "país": "Chile",
    "stock": 30,
    "valor del producto": 2800.00,
    "fecha de exhibición": "2025-10-03",
    "imagen": "../images/image11.jpg"
  },
  {
    "id": 12,
    "Nombre de película": "Sombras del pasado",
    "duracion": 100,
    "director": "Alfonso Vega",
    "año de realización": 2011,
    "país": "Francia",
    "stock": 6,
    "valor del producto": 8700.00,
    "fecha de exhibición": "2025-11-22",
    "imagen": "../images/image12.jpg"
  },
  {
    "id": 13,
    "Nombre de película": "El jardín mecánico",
    "duracion": 110,
    "director": "Marcos Pinto",
    "año de realización": 2012,
    "país": "Brasil",
    "stock": 9,
    "valor del producto": 6600.00,
    "fecha de exhibición": "2025-10-18",
    "imagen": "../images/image13.jpg"
  },
  {
    "id": 14,
    "Nombre de película": "Ritmo de ciudad",
    "duracion": 93,
    "director": "Valeria Soto",
    "año de realización": 2010,
    "país": "Estados Unidos",
    "stock": 11,
    "valor del producto": 4700.50,
    "fecha de exhibición": "2025-09-29",
    "imagen": "../images/image14.jpg"
  },
  {
    "id": 15,
    "Nombre de película": "El espejo azul",
    "duracion": 100,
    "director": "Héctor Oliva",
    "año de realización": 2009,
    "país": "Italia",
    "stock": 3,
    "valor del producto": 13900.00,
    "fecha de exhibición": "2025-12-10",
    "imagen": "../images/image15.jpg"
  },
  {
    "id": 16,
    "Nombre de película": "Pájaros de papel",
    "duracion": 86,
    "director": "Camila Rojas",
    "año de realización": 2023,
    "país": "Chile",
    "stock": 22,
    "valor del producto": 3600.00,
    "fecha de exhibición": "2025-10-11",
    "imagen": "../images/image16.jpg"
  },
  {
    "id": 17,
    "Nombre de película": "Niebla sobre la playa",
    "duracion": 119,
    "director": "Federico Santos",
    "año de realización": 2018,
    "país": "Portugal",
    "stock": 13,
    "valor del producto": 5900.00,
    "fecha de exhibición": "2025-10-27",
    "imagen": "../images/image17.jpg"
  },
  {
    "id": 18,
    "Nombre de película": "Huellas en la nieve",
    "duracion": 130,
    "director": "Olga Martín",
    "año de realización": 2007,
    "país": "Suecia",
    "stock": 2,
    "valor del producto": 15000.00,
    "fecha de exhibición": "2025-12-20",
    "imagen": "../images/image18.jpg"
  },
  {
    "id": 19,
    "Nombre de película": "Sonata para dos",
    "duracion": 105,
    "director": "Ricardo Luna",
    "año de realización": 2016,
    "país": "Chile",
    "stock": 16,
    "valor del producto": 5200.00,
    "fecha de exhibición": "2025-11-05",
    "imagen": "../images/image19.jpg"
  },
  {
    "id": 20,
    "Nombre de película": "Viaje a la deriva",
    "duracion": 118,
    "director": "Elsa Cabrera",
    "año de realización": 2021,
    "país": "Bolivia",
    "stock": 15,
    "valor del producto": 6000.00,
    "fecha de exhibición": "2025-10-17",
    "imagen": "../images/image20.jpg"
  },
  {
    "id": 21,
    "Nombre de película": "La última estación",
    "duracion": 132,
    "director": "Gonzalo Ibáñez",
    "año de realización": 2014,
    "país": "Canadá",
    "stock": 1,
    "valor del producto": 17200.99,
    "fecha de exhibición": "2025-12-31",
    "imagen": "../images/image21.jpg"
  }
]
